ML_platform/utils.py
hss_ml-1.0.1.dist-info/METADATA
hss_ml-1.0.1.dist-info/RECORD
hss_ml-1.0.1.dist-info/WHEEL
hss_ml-1.0.1.dist-info/top_level.txt
