Metadata-Version: 2.1
Name: hss-ml
Version: 1.0.1
Summary: hss的机器学习包
Home-page: UNKNOWN
Author: hss
Author-email: 1046525663@qq.com
License: UNKNOWN
Platform: UNKNOWN
Classifier: Programming Language :: Python :: 3
Classifier: License :: OSI Approved :: MIT License
Classifier: Operating System :: OS Independent
Requires-Python: >=3.0, !=3.0.*, !=3.1.*, !=3.2.*, !=3.3*
Requires-Dist: numpy
